setup.cfg
setup.py
merky/__init__.py
merky/digest.py
merky/serialization.py
merky/transformer.py
merky/tree.py
merky/util.py
merky.egg-info/PKG-INFO
merky.egg-info/SOURCES.txt
merky.egg-info/dependency_links.txt
merky.egg-info/requires.txt
merky.egg-info/top_level.txt
merky/cases/__init__.py
merky/cases/attrgraph.py
merky/cases/tokendict.py
merky/cases/walker.py
merky/store/__init__.py
merky/store/structure.py
merky/test/__init__.py
merky/test/annotation_nesting_test.py
merky/test/any_nesting_test.py
merky/test/exclude_annotation_nesting_test.py
merky/test/generate_samples.py
merky/test/py2.py
merky/test/py3.py
merky/test/samples.py
merky/test/words.py
merky/test/misc/__init__.py
merky/test/misc/graph_storage_test.py
merky/test/store/__init__.py
merky/test/store/structure_test.py
merky/test/usecases/__init__.py
merky/test/usecases/attribute_graph_test.py
merky/test/usecases/tokendict_test.py
merky/test/usecases/walker_test.py