Metadata-Version: 1.0
Name: merky
Version: 0.1.0
Summary: JSON-oriented merkle tree utilities
Home-page: https://github.com/ethanrowe/python-merky
Author: Ethan Rowe
Author-email: ethan@the-rowes.com
License: MIT
Platform: UNKNOWN
